rsgt/__init__.py
rsgt/augmentation.py
rsgt/normalization.py
rsgt-1.1.0.dist-info/LICENSE
rsgt-1.1.0.dist-info/METADATA
rsgt-1.1.0.dist-info/WHEEL
rsgt-1.1.0.dist-info/top_level.txt
rsgt-1.1.0.dist-info/RECORD
