Metadata-Version: 2.1
Name: rsgt
Version: 1.1.0
Summary: Implementaton of random smooth gray value transformations (rsgt) for training gray value independent neural networks
Home-page: https://github.com/nlessmann/rsgt
License: UNKNOWN
Platform: UNKNOWN
Classifier: Programming Language :: Python :: 2
Classifier: Programming Language :: Python :: 3
Classifier: License :: OSI Approved :: MIT License
Classifier: Operating System :: OS Independent
Requires-Python: >=2.7
Requires-Dist: numpy
